{"images": [{"video_no": 69483, "img_no": 1391179, "img_path": "/201909_3W_B1/20190917/28-8-Camera 10 (805316626)/28-8-Camera 10 (805316626)_9.jpg", "width": 1920, "height": 1080, "action_category": "28"}, {"video_no": 69483, "img_no": 1391180, "img_path": "/201909_3W_B1/20190917/28-8-Camera 10 (805316626)/28-8-Camera 10 (805316626)_19.jpg", "width": 1920, "height": 1080, "action_category": "28"}, {"video_no": 69483, "img_no": 1391181, "img_path": "/201909_3W_B1/20190917/28-8-Camera 10 (805316626)/28-8-Camera 10 (805316626)_29.jpg", "width": 1920, "height": 1080, "action_category": "28"}, {"video_no": 69483, "img_no": 1391182, "img_path": "/201909_3W_B1/20190917/28-8-Camera 10 (805316626)/28-8-Camera 10 (805316626)_39.jpg", "width": 1920, "height": 1080, "action_category": "28"}, {"video_no": 69483, "img_no": 1391183, "img_path": "/201909_3W_B1/20190917/28-8-Camera 10 (805316626)/28-8-Camera 10 (805316626)_49.jpg", "width": 1920, "height": 1080, "action_category": "28"}, {"video_no": 69483, "img_no": 1391184, "img_path": "/201909_3W_B1/20190917/28-8-Camera 10 (805316626)/28-8-Camera 10 (805316626)_59.jpg", "width": 1920, "height": 1080, "action_category": "28"}, {"video_no": 69483, "img_no": 1391185, "img_path": "/201909_3W_B1/20190917/28-8-Camera 10 (805316626)/28-8-Camera 10 (805316626)_69.jpg", "width": 1920, "height": 1080, "action_category": "28"}, {"video_no": 69483, "img_no": 1391186, "img_path": "/201909_3W_B1/20190917/28-8-Camera 10 (805316626)/28-8-Camera 10 (805316626)_79.jpg", "width": 1920, "height": 1080, "action_category": "28"}, {"video_no": 69483, "img_no": 1391187, "img_path": "/201909_3W_B1/20190917/28-8-Camera 10 (805316626)/28-8-Camera 10 (805316626)_89.jpg", "width": 1920, "height": 1080, "action_category": "28"}, {"video_no": 69483, "img_no": 1391188, "img_path": "/201909_3W_B1/20190917/28-8-Camera 10 (805316626)/28-8-Camera 10 (805316626)_99.jpg", "width": 1920, "height": 1080, "action_category": "28"}, {"video_no": 69483, "img_no": 1391189, "img_path": "/201909_3W_B1/20190917/28-8-Camera 10 (805316626)/28-8-Camera 10 (805316626)_109.jpg", "width": 1920, "height": 1080, "action_category": "28"}, {"video_no": 69483, "img_no": 1391190, "img_path": "/201909_3W_B1/20190917/28-8-Camera 10 (805316626)/28-8-Camera 10 (805316626)_119.jpg", "width": 1920, "height": 1080, "action_category": "28"}, {"video_no": 69483, "img_no": 1391191, "img_path": "/201909_3W_B1/20190917/28-8-Camera 10 (805316626)/28-8-Camera 10 (805316626)_129.jpg", "width": 1920, "height": 1080, "action_category": "28"}, {"video_no": 69483, "img_no": 1391192, "img_path": "/201909_3W_B1/20190917/28-8-Camera 10 (805316626)/28-8-Camera 10 (805316626)_139.jpg", "width": 1920, "height": 1080, "action_category": "28"}, {"video_no": 69483, "img_no": 1391193, "img_path": "/201909_3W_B1/20190917/28-8-Camera 10 (805316626)/28-8-Camera 10 (805316626)_149.jpg", "width": 1920, "height": 1080, "action_category": "28"}, {"video_no": 69483, "img_no": 1391194, "img_path": "/201909_3W_B1/20190917/28-8-Camera 10 (805316626)/28-8-Camera 10 (805316626)_159.jpg", "width": 1920, "height": 1080, "action_category": "28"}, {"video_no": 69483, "img_no": 1391195, "img_path": "/201909_3W_B1/20190917/28-8-Camera 10 (805316626)/28-8-Camera 10 (805316626)_169.jpg", "width": 1920, "height": 1080, "action_category": "28"}, {"video_no": 69483, "img_no": 1391196, "img_path": "/201909_3W_B1/20190917/28-8-Camera 10 (805316626)/28-8-Camera 10 (805316626)_179.jpg", "width": 1920, "height": 1080, "action_category": "28"}], "categories": [{"supercategory": "person", "id": 1, "name": "person", "keypoints": ["right_ankle_x", "right_ankle_y", "right_ankle_view", "right_knee_x", "right_knee_y", "right_knee_view", "right_hip_x", "right_hip_y", "right_hip_view", "left_hip_x", "left_hip_y", "left_hip_view", "left_knee_x", "left_knee_y", "left_knee_view", "left_ankle_x", "left_ankle_y", "left_ankle_view", "pelvis_x", "pelvis_y", "pelvis_view", "throax_x", "throax_y", "throax_view", "neck_x", "neck_y", "neck_view", "head_top_x", "head_top_y", "head_top_view", "right_wrist_x", "right_wrist_y", "right_wrist_view", "right_elbow_x", "right_elbow_y", "right_elbow_view", "right_shoulder_x", "right_shoulder_y", "right_shoulder_view", "left_shoulder_x", "left_shoulder_y", "left_shoulder_view", "left_elbow_x", "left_elbow_y", "left_elbow_view", "left_wrist_x", "left_wrist_y", "left_wrist_view"]}], "annotations": [{"img_no": 1391179, "person_no": 1, "bbox": [687.0, 99.0, 1238.0, 767.0], "keypoints": [915.0, 702.0, 2.0, 923.0, 551.0, 2.0, 958.0, 422.0, 2.0, 1030.0, 422.0, 2.0, 1045.0, 565.0, 2.0, 1066.0, 730.0, 2.0, 994.0, 422.0, 2.0, 958.0, 242.0, 2.0, 951.0, 221.0, 2.0, 908.0, 120.0, 2.0, 851.0, 458.0, 2.0, 872.0, 350.0, 2.0, 901.0, 250.0, 2.0, 1023.0, 235.0, 2.0, 1052.0, 357.0, 2.0, 1037.0, 465.0, 2.0], "num_keypoint": 16}, {"img_no": 1391180, "person_no": 1, "bbox": [910.0, 55.0, 1272.0, 964.0], "keypoints": [1184.0, 851.0, 2.0, 1184.0, 682.0, 2.0, 1219.0, 478.0, 2.0, 1113.0, 496.0, 2.0, 1024.0, 682.0, 2.0, 980.0, 895.0, 2.0, 1166.0, 487.0, 2.0, 1104.0, 247.0, 2.0, 1095.0, 203.0, 2.0, 1068.0, 61.0, 2.0, 1175.0, 469.0, 2.0, 1201.0, 371.0, 2.0, 1184.0, 238.0, 2.0, 1015.0, 256.0, 2.0, 971.0, 407.0, 2.0, 944.0, 531.0, 2.0], "num_keypoint": 16}, {"img_no": 1391181, "person_no": 1, "bbox": [910.0, 55.0, 1272.0, 964.0], "keypoints": [1184.0, 851.0, 2.0, 1184.0, 682.0, 2.0, 1219.0, 496.0, 2.0, 1130.0, 505.0, 2.0, 1024.0, 682.0, 2.0, 988.0, 895.0, 2.0, 1175.0, 505.0, 2.0, 1104.0, 265.0, 2.0, 1104.0, 212.0, 2.0, 1095.0, 87.0, 2.0, 1148.0, 478.0, 2.0, 1193.0, 380.0, 2.0, 1184.0, 256.0, 2.0, 1015.0, 274.0, 2.0, 980.0, 425.0, 2.0, 980.0, 549.0, 2.0], "num_keypoint": 16}, {"img_no": 1391182, "person_no": 1, "bbox": [910.0, 74.0, 1262.0, 956.0], "keypoints": [1185.0, 846.0, 2.0, 1185.0, 691.0, 2.0, 1219.0, 510.0, 2.0, 1116.0, 519.0, 2.0, 1021.0, 691.0, 2.0, 986.0, 889.0, 2.0, 1176.0, 510.0, 2.0, 1098.0, 269.0, 2.0, 1098.0, 217.0, 2.0, 1107.0, 88.0, 2.0, 1141.0, 493.0, 2.0, 1193.0, 398.0, 2.0, 1176.0, 260.0, 2.0, 1012.0, 278.0, 2.0, 986.0, 424.0, 2.0, 978.0, 553.0, 2.0], "num_keypoint": 16}, {"img_no": 1391183, "person_no": 1, "bbox": [910.0, 74.0, 1262.0, 956.0], "keypoints": [1185.0, 846.0, 2.0, 1185.0, 691.0, 2.0, 1228.0, 510.0, 2.0, 1124.0, 510.0, 2.0, 1012.0, 691.0, 2.0, 986.0, 898.0, 2.0, 1176.0, 510.0, 2.0, 1116.0, 269.0, 2.0, 1107.0, 217.0, 2.0, 1098.0, 88.0, 2.0, 1219.0, 493.0, 2.0, 1253.0, 398.0, 2.0, 1202.0, 260.0, 2.0, 1021.0, 278.0, 2.0, 961.0, 424.0, 2.0, 900.0, 536.0, 2.0], "num_keypoint": 16}, {"img_no": 1391184, "person_no": 1, "bbox": [910.0, 74.0, 1262.0, 956.0], "keypoints": [1185.0, 846.0, 2.0, 1185.0, 691.0, 2.0, 1228.0, 510.0, 2.0, 1133.0, 510.0, 2.0, 1021.0, 682.0, 2.0, 986.0, 898.0, 2.0, 1176.0, 510.0, 2.0, 1116.0, 260.0, 2.0, 1107.0, 217.0, 2.0, 1098.0, 80.0, 2.0, 1331.0, 372.0, 2.0, 1288.0, 329.0, 2.0, 1193.0, 252.0, 2.0, 1021.0, 278.0, 2.0, 926.0, 381.0, 2.0, 788.0, 433.0, 2.0], "num_keypoint": 16}, {"img_no": 1391185, "person_no": 1, "bbox": [705.0, 55.0, 1427.0, 978.0], "keypoints": [1183.0, 859.0, 2.0, 1183.0, 690.0, 2.0, 1221.0, 502.0, 2.0, 1136.0, 511.0, 2.0, 1014.0, 681.0, 2.0, 986.0, 887.0, 2.0, 1174.0, 511.0, 2.0, 1117.0, 257.0, 2.0, 1098.0, 220.0, 2.0, 1080.0, 88.0, 2.0, 1343.0, 323.0, 2.0, 1277.0, 314.0, 2.0, 1192.0, 248.0, 2.0, 1042.0, 276.0, 2.0, 920.0, 351.0, 2.0, 788.0, 370.0, 2.0], "num_keypoint": 16}, {"img_no": 1391186, "person_no": 1, "bbox": [705.0, 55.0, 1427.0, 978.0], "keypoints": [1183.0, 850.0, 2.0, 1183.0, 681.0, 2.0, 1221.0, 502.0, 2.0, 1127.0, 511.0, 2.0, 1014.0, 681.0, 2.0, 976.0, 897.0, 2.0, 1174.0, 511.0, 2.0, 1117.0, 267.0, 2.0, 1108.0, 210.0, 2.0, 1089.0, 88.0, 2.0, 1333.0, 361.0, 2.0, 1268.0, 323.0, 2.0, 1192.0, 248.0, 2.0, 1033.0, 276.0, 2.0, 910.0, 361.0, 2.0, 779.0, 389.0, 2.0], "num_keypoint": 16}, {"img_no": 1391187, "person_no": 1, "bbox": [705.0, 55.0, 1427.0, 978.0], "keypoints": [1183.0, 850.0, 2.0, 1183.0, 690.0, 2.0, 1230.0, 492.0, 2.0, 1127.0, 492.0, 2.0, 1023.0, 690.0, 2.0, 976.0, 897.0, 2.0, 1183.0, 492.0, 2.0, 1117.0, 257.0, 2.0, 1108.0, 210.0, 2.0, 1089.0, 79.0, 2.0, 1258.0, 483.0, 2.0, 1268.0, 370.0, 2.0, 1202.0, 248.0, 2.0, 1033.0, 276.0, 2.0, 939.0, 408.0, 2.0, 845.0, 492.0, 2.0], "num_keypoint": 16}, {"img_no": 1391188, "person_no": 1, "bbox": [705.0, 55.0, 1427.0, 978.0], "keypoints": [1183.0, 850.0, 2.0, 1183.0, 690.0, 2.0, 1230.0, 492.0, 2.0, 1127.0, 492.0, 2.0, 1023.0, 690.0, 2.0, 976.0, 897.0, 2.0, 1183.0, 492.0, 2.0, 1117.0, 257.0, 2.0, 1108.0, 210.0, 2.0, 1089.0, 79.0, 2.0, 1258.0, 483.0, 2.0, 1268.0, 370.0, 2.0, 1202.0, 248.0, 2.0, 1033.0, 276.0, 2.0, 939.0, 408.0, 2.0, 845.0, 492.0, 2.0], "num_keypoint": 16}, {"img_no": 1391189, "person_no": 1, "bbox": [898.0, 36.0, 1256.0, 944.0], "keypoints": [1178.0, 849.0, 2.0, 1178.0, 689.0, 2.0, 1205.0, 494.0, 2.0, 1108.0, 512.0, 2.0, 1010.0, 689.0, 2.0, 975.0, 884.0, 2.0, 1161.0, 503.0, 2.0, 1099.0, 263.0, 2.0, 1090.0, 210.0, 2.0, 1072.0, 86.0, 2.0, 1134.0, 476.0, 2.0, 1187.0, 370.0, 2.0, 1178.0, 246.0, 2.0, 1010.0, 272.0, 2.0, 983.0, 414.0, 2.0, 983.0, 538.0, 2.0], "num_keypoint": 16}, {"img_no": 1391190, "person_no": 1, "bbox": [898.0, 36.0, 1256.0, 944.0], "keypoints": [1178.0, 840.0, 2.0, 1178.0, 689.0, 2.0, 1205.0, 494.0, 2.0, 1108.0, 512.0, 2.0, 1010.0, 689.0, 2.0, 975.0, 884.0, 2.0, 1161.0, 503.0, 2.0, 1090.0, 263.0, 2.0, 1090.0, 210.0, 2.0, 1072.0, 86.0, 2.0, 1134.0, 476.0, 2.0, 1178.0, 370.0, 2.0, 1178.0, 246.0, 2.0, 1010.0, 272.0, 2.0, 975.0, 423.0, 2.0, 966.0, 547.0, 2.0], "num_keypoint": 16}, {"img_no": 1391191, "person_no": 1, "bbox": [802.0, 65.0, 1273.0, 974.0], "keypoints": [1183.0, 852.0, 2.0, 1175.0, 692.0, 2.0, 1210.0, 497.0, 2.0, 1112.0, 506.0, 2.0, 1015.0, 692.0, 2.0, 979.0, 896.0, 2.0, 1157.0, 506.0, 2.0, 1095.0, 257.0, 2.0, 1086.0, 213.0, 2.0, 1059.0, 80.0, 2.0, 1246.0, 461.0, 2.0, 1254.0, 364.0, 2.0, 1183.0, 248.0, 2.0, 1006.0, 275.0, 2.0, 926.0, 408.0, 2.0, 846.0, 515.0, 2.0], "num_keypoint": 16}, {"img_no": 1391192, "person_no": 1, "bbox": [802.0, 65.0, 1273.0, 974.0], "keypoints": [1183.0, 852.0, 2.0, 1175.0, 683.0, 2.0, 1219.0, 488.0, 2.0, 1121.0, 488.0, 2.0, 1015.0, 683.0, 2.0, 979.0, 896.0, 2.0, 1175.0, 488.0, 2.0, 1086.0, 257.0, 2.0, 1077.0, 213.0, 2.0, 1068.0, 80.0, 2.0, 1130.0, 444.0, 2.0, 1192.0, 319.0, 2.0, 1157.0, 257.0, 2.0, 1015.0, 266.0, 2.0, 908.0, 364.0, 2.0, 766.0, 408.0, 2.0], "num_keypoint": 16}, {"img_no": 1391193, "person_no": 1, "bbox": [802.0, 65.0, 1273.0, 974.0], "keypoints": [1175.0, 852.0, 2.0, 1175.0, 683.0, 2.0, 1210.0, 488.0, 2.0, 1121.0, 497.0, 2.0, 1015.0, 683.0, 2.0, 979.0, 896.0, 2.0, 1166.0, 488.0, 2.0, 1086.0, 257.0, 2.0, 1077.0, 213.0, 2.0, 1059.0, 80.0, 2.0, 1130.0, 417.0, 2.0, 1166.0, 319.0, 2.0, 1157.0, 248.0, 2.0, 1015.0, 266.0, 2.0, 899.0, 346.0, 2.0, 766.0, 373.0, 2.0], "num_keypoint": 16}, {"img_no": 1391194, "person_no": 1, "bbox": [693.0, 55.0, 1406.0, 978.0], "keypoints": [1184.0, 846.0, 2.0, 1184.0, 678.0, 2.0, 1202.0, 493.0, 2.0, 1109.0, 511.0, 2.0, 1007.0, 688.0, 2.0, 979.0, 892.0, 2.0, 1156.0, 502.0, 2.0, 1091.0, 261.0, 2.0, 1081.0, 214.0, 2.0, 1063.0, 84.0, 2.0, 1341.0, 363.0, 2.0, 1267.0, 316.0, 2.0, 1174.0, 242.0, 2.0, 1007.0, 279.0, 2.0, 896.0, 372.0, 2.0, 766.0, 419.0, 2.0], "num_keypoint": 16}, {"img_no": 1391195, "person_no": 1, "bbox": [693.0, 55.0, 1406.0, 978.0], "keypoints": [1184.0, 855.0, 2.0, 1184.0, 688.0, 2.0, 1211.0, 502.0, 2.0, 1109.0, 511.0, 2.0, 1007.0, 688.0, 2.0, 979.0, 892.0, 2.0, 1156.0, 502.0, 2.0, 1100.0, 261.0, 2.0, 1081.0, 214.0, 2.0, 1054.0, 84.0, 2.0, 1286.0, 465.0, 2.0, 1258.0, 363.0, 2.0, 1184.0, 251.0, 2.0, 1007.0, 279.0, 2.0, 933.0, 419.0, 2.0, 840.0, 521.0, 2.0], "num_keypoint": 16}, {"img_no": 1391196, "person_no": 1, "bbox": [693.0, 55.0, 1406.0, 978.0], "keypoints": [1184.0, 846.0, 2.0, 1184.0, 688.0, 2.0, 1211.0, 502.0, 2.0, 1119.0, 511.0, 2.0, 1007.0, 688.0, 2.0, 979.0, 892.0, 2.0, 1156.0, 502.0, 2.0, 1091.0, 261.0, 2.0, 1081.0, 214.0, 2.0, 1063.0, 84.0, 2.0, 1156.0, 484.0, 2.0, 1193.0, 391.0, 2.0, 1174.0, 251.0, 2.0, 1007.0, 279.0, 2.0, 961.0, 419.0, 2.0, 924.0, 548.0, 2.0], "num_keypoint": 16}]}