{"images": [{"video_no": 69489, "img_no": 1391287, "img_path": "/201909_3W_B1/20190917/28-8-Camera 5 (805316621)/28-8-Camera 5 (805316621)_9.jpg", "width": 1920, "height": 1080, "action_category": "28"}, {"video_no": 69489, "img_no": 1391288, "img_path": "/201909_3W_B1/20190917/28-8-Camera 5 (805316621)/28-8-Camera 5 (805316621)_19.jpg", "width": 1920, "height": 1080, "action_category": "28"}, {"video_no": 69489, "img_no": 1391289, "img_path": "/201909_3W_B1/20190917/28-8-Camera 5 (805316621)/28-8-Camera 5 (805316621)_29.jpg", "width": 1920, "height": 1080, "action_category": "28"}, {"video_no": 69489, "img_no": 1391290, "img_path": "/201909_3W_B1/20190917/28-8-Camera 5 (805316621)/28-8-Camera 5 (805316621)_39.jpg", "width": 1920, "height": 1080, "action_category": "28"}, {"video_no": 69489, "img_no": 1391291, "img_path": "/201909_3W_B1/20190917/28-8-Camera 5 (805316621)/28-8-Camera 5 (805316621)_49.jpg", "width": 1920, "height": 1080, "action_category": "28"}, {"video_no": 69489, "img_no": 1391292, "img_path": "/201909_3W_B1/20190917/28-8-Camera 5 (805316621)/28-8-Camera 5 (805316621)_59.jpg", "width": 1920, "height": 1080, "action_category": "28"}, {"video_no": 69489, "img_no": 1391293, "img_path": "/201909_3W_B1/20190917/28-8-Camera 5 (805316621)/28-8-Camera 5 (805316621)_69.jpg", "width": 1920, "height": 1080, "action_category": "28"}, {"video_no": 69489, "img_no": 1391294, "img_path": "/201909_3W_B1/20190917/28-8-Camera 5 (805316621)/28-8-Camera 5 (805316621)_79.jpg", "width": 1920, "height": 1080, "action_category": "28"}, {"video_no": 69489, "img_no": 1391295, "img_path": "/201909_3W_B1/20190917/28-8-Camera 5 (805316621)/28-8-Camera 5 (805316621)_89.jpg", "width": 1920, "height": 1080, "action_category": "28"}, {"video_no": 69489, "img_no": 1391296, "img_path": "/201909_3W_B1/20190917/28-8-Camera 5 (805316621)/28-8-Camera 5 (805316621)_99.jpg", "width": 1920, "height": 1080, "action_category": "28"}, {"video_no": 69489, "img_no": 1391297, "img_path": "/201909_3W_B1/20190917/28-8-Camera 5 (805316621)/28-8-Camera 5 (805316621)_109.jpg", "width": 1920, "height": 1080, "action_category": "28"}, {"video_no": 69489, "img_no": 1391298, "img_path": "/201909_3W_B1/20190917/28-8-Camera 5 (805316621)/28-8-Camera 5 (805316621)_119.jpg", "width": 1920, "height": 1080, "action_category": "28"}, {"video_no": 69489, "img_no": 1391299, "img_path": "/201909_3W_B1/20190917/28-8-Camera 5 (805316621)/28-8-Camera 5 (805316621)_129.jpg", "width": 1920, "height": 1080, "action_category": "28"}, {"video_no": 69489, "img_no": 1391300, "img_path": "/201909_3W_B1/20190917/28-8-Camera 5 (805316621)/28-8-Camera 5 (805316621)_139.jpg", "width": 1920, "height": 1080, "action_category": "28"}, {"video_no": 69489, "img_no": 1391301, "img_path": "/201909_3W_B1/20190917/28-8-Camera 5 (805316621)/28-8-Camera 5 (805316621)_149.jpg", "width": 1920, "height": 1080, "action_category": "28"}, {"video_no": 69489, "img_no": 1391302, "img_path": "/201909_3W_B1/20190917/28-8-Camera 5 (805316621)/28-8-Camera 5 (805316621)_159.jpg", "width": 1920, "height": 1080, "action_category": "28"}, {"video_no": 69489, "img_no": 1391303, "img_path": "/201909_3W_B1/20190917/28-8-Camera 5 (805316621)/28-8-Camera 5 (805316621)_169.jpg", "width": 1920, "height": 1080, "action_category": "28"}, {"video_no": 69489, "img_no": 1391304, "img_path": "/201909_3W_B1/20190917/28-8-Camera 5 (805316621)/28-8-Camera 5 (805316621)_179.jpg", "width": 1920, "height": 1080, "action_category": "28"}], "categories": [{"supercategory": "person", "id": 1, "name": "person", "keypoints": ["right_ankle_x", "right_ankle_y", "right_ankle_view", "right_knee_x", "right_knee_y", "right_knee_view", "right_hip_x", "right_hip_y", "right_hip_view", "left_hip_x", "left_hip_y", "left_hip_view", "left_knee_x", "left_knee_y", "left_knee_view", "left_ankle_x", "left_ankle_y", "left_ankle_view", "pelvis_x", "pelvis_y", "pelvis_view", "throax_x", "throax_y", "throax_view", "neck_x", "neck_y", "neck_view", "head_top_x", "head_top_y", "head_top_view", "right_wrist_x", "right_wrist_y", "right_wrist_view", "right_elbow_x", "right_elbow_y", "right_elbow_view", "right_shoulder_x", "right_shoulder_y", "right_shoulder_view", "left_shoulder_x", "left_shoulder_y", "left_shoulder_view", "left_elbow_x", "left_elbow_y", "left_elbow_view", "left_wrist_x", "left_wrist_y", "left_wrist_view"]}], "annotations": [{"img_no": 1391287, "person_no": 1, "bbox": [840.0, 260.0, 1128.0, 997.0], "keypoints": [982.0, 849.0, 2.0, 975.0, 707.0, 2.0, 983.0, 575.0, 2.0, 1019.0, 578.0, 2.0, 1037.0, 756.0, 2.0, 1052.0, 902.0, 2.0, 999.0, 576.0, 2.0, 981.0, 473.0, 2.0, 961.0, 373.0, 2.0, 894.0, 286.0, 2.0, 910.0, 576.0, 2.0, 938.0, 512.0, 2.0, 949.0, 409.0, 2.0, 1022.0, 422.0, 2.0, 1039.0, 553.0, 2.0, 1014.0, 655.0, 2.0], "num_keypoint": 16}, {"img_no": 1391288, "person_no": 1, "bbox": [840.0, 260.0, 1128.0, 997.0], "keypoints": [982.0, 849.0, 2.0, 975.0, 707.0, 1.0, 983.0, 575.0, 2.0, 1019.0, 578.0, 1.0, 1037.0, 756.0, 2.0, 1052.0, 902.0, 2.0, 999.0, 576.0, 1.0, 981.0, 473.0, 2.0, 961.0, 373.0, 2.0, 894.0, 286.0, 2.0, 916.0, 610.0, 2.0, 930.0, 516.0, 2.0, 917.0, 401.0, 2.0, 1004.0, 421.0, 2.0, 1010.0, 567.0, 2.0, 983.0, 686.0, 2.0], "num_keypoint": 16}, {"img_no": 1391289, "person_no": 1, "bbox": [840.0, 260.0, 1128.0, 997.0], "keypoints": [982.0, 849.0, 2.0, 975.0, 707.0, 1.0, 972.0, 584.0, 1.0, 1030.0, 584.0, 1.0, 1037.0, 756.0, 2.0, 1052.0, 902.0, 2.0, 995.0, 582.0, 1.0, 955.0, 498.0, 1.0, 918.0, 403.0, 2.0, 907.0, 293.0, 2.0, 895.0, 641.0, 2.0, 920.0, 541.0, 2.0, 898.0, 427.0, 2.0, 985.0, 429.0, 2.0, 1012.0, 597.0, 2.0, 964.0, 689.0, 2.0], "num_keypoint": 16}, {"img_no": 1391290, "person_no": 1, "bbox": [840.0, 260.0, 1128.0, 997.0], "keypoints": [982.0, 849.0, 2.0, 975.0, 707.0, 1.0, 983.0, 575.0, 1.0, 1019.0, 578.0, 2.0, 1037.0, 756.0, 2.0, 1052.0, 902.0, 2.0, 999.0, 576.0, 1.0, 961.0, 481.0, 1.0, 932.0, 396.0, 2.0, 894.0, 286.0, 2.0, 905.0, 639.0, 2.0, 919.0, 556.0, 2.0, 905.0, 425.0, 2.0, 996.0, 440.0, 2.0, 990.0, 586.0, 2.0, 953.0, 690.0, 2.0], "num_keypoint": 16}, {"img_no": 1391291, "person_no": 1, "bbox": [825.0, 271.0, 1113.0, 1008.0], "keypoints": [982.0, 849.0, 2.0, 975.0, 707.0, 1.0, 983.0, 575.0, 1.0, 1019.0, 578.0, 2.0, 1037.0, 756.0, 2.0, 1052.0, 902.0, 2.0, 999.0, 576.0, 1.0, 968.0, 481.0, 1.0, 936.0, 391.0, 2.0, 894.0, 286.0, 2.0, 866.0, 578.0, 2.0, 918.0, 503.0, 2.0, 914.0, 418.0, 2.0, 996.0, 440.0, 2.0, 1012.0, 585.0, 2.0, 968.0, 682.0, 2.0], "num_keypoint": 16}, {"img_no": 1391292, "person_no": 1, "bbox": [798.0, 281.0, 1126.0, 1018.0], "keypoints": [982.0, 849.0, 2.0, 975.0, 707.0, 2.0, 983.0, 575.0, 2.0, 1019.0, 578.0, 2.0, 1037.0, 756.0, 2.0, 1052.0, 902.0, 2.0, 999.0, 576.0, 2.0, 968.0, 481.0, 2.0, 936.0, 391.0, 2.0, 894.0, 286.0, 2.0, 841.0, 465.0, 2.0, 908.0, 434.0, 2.0, 920.0, 408.0, 2.0, 1012.0, 423.0, 2.0, 1082.0, 520.0, 2.0, 1056.0, 606.0, 2.0], "num_keypoint": 16}, {"img_no": 1391293, "person_no": 1, "bbox": [798.0, 281.0, 1126.0, 1018.0], "keypoints": [982.0, 849.0, 2.0, 975.0, 707.0, 2.0, 983.0, 575.0, 2.0, 1019.0, 578.0, 2.0, 1037.0, 756.0, 2.0, 1052.0, 902.0, 2.0, 999.0, 576.0, 2.0, 968.0, 481.0, 2.0, 936.0, 391.0, 2.0, 897.0, 306.0, 2.0, 839.0, 419.0, 2.0, 893.0, 422.0, 2.0, 920.0, 408.0, 1.0, 1011.0, 408.0, 2.0, 1095.0, 486.0, 2.0, 1081.0, 549.0, 2.0], "num_keypoint": 16}, {"img_no": 1391294, "person_no": 1, "bbox": [798.0, 281.0, 1126.0, 1018.0], "keypoints": [982.0, 849.0, 2.0, 975.0, 707.0, 2.0, 983.0, 575.0, 2.0, 1019.0, 578.0, 2.0, 1037.0, 756.0, 2.0, 1052.0, 902.0, 2.0, 999.0, 576.0, 2.0, 968.0, 481.0, 2.0, 936.0, 391.0, 2.0, 897.0, 306.0, 2.0, 837.0, 469.0, 2.0, 906.0, 432.0, 2.0, 920.0, 408.0, 1.0, 1011.0, 408.0, 2.0, 1075.0, 507.0, 2.0, 1048.0, 597.0, 2.0], "num_keypoint": 16}, {"img_no": 1391295, "person_no": 1, "bbox": [798.0, 281.0, 1126.0, 1018.0], "keypoints": [982.0, 849.0, 2.0, 975.0, 707.0, 2.0, 983.0, 575.0, 2.0, 1019.0, 578.0, 2.0, 1037.0, 756.0, 2.0, 1052.0, 902.0, 2.0, 999.0, 576.0, 1.0, 968.0, 481.0, 2.0, 936.0, 391.0, 2.0, 897.0, 306.0, 2.0, 855.0, 572.0, 2.0, 917.0, 487.0, 2.0, 920.0, 408.0, 2.0, 1011.0, 408.0, 2.0, 1030.0, 553.0, 2.0, 993.0, 659.0, 2.0], "num_keypoint": 16}, {"img_no": 1391296, "person_no": 1, "bbox": [798.0, 281.0, 1126.0, 1018.0], "keypoints": [982.0, 849.0, 2.0, 975.0, 707.0, 2.0, 983.0, 575.0, 2.0, 1019.0, 578.0, 2.0, 1037.0, 756.0, 2.0, 1052.0, 902.0, 2.0, 999.0, 576.0, 1.0, 968.0, 481.0, 2.0, 936.0, 391.0, 2.0, 897.0, 306.0, 2.0, 882.0, 612.0, 2.0, 917.0, 487.0, 2.0, 920.0, 408.0, 2.0, 1003.0, 428.0, 2.0, 1023.0, 565.0, 2.0, 972.0, 678.0, 2.0], "num_keypoint": 16}, {"img_no": 1391297, "person_no": 1, "bbox": [798.0, 281.0, 1126.0, 1018.0], "keypoints": [982.0, 849.0, 2.0, 975.0, 707.0, 2.0, 983.0, 575.0, 2.0, 1019.0, 578.0, 2.0, 1037.0, 756.0, 2.0, 1052.0, 902.0, 2.0, 999.0, 576.0, 1.0, 968.0, 481.0, 2.0, 936.0, 391.0, 2.0, 897.0, 306.0, 2.0, 903.0, 633.0, 2.0, 923.0, 541.0, 2.0, 920.0, 408.0, 2.0, 1003.0, 428.0, 2.0, 1023.0, 565.0, 2.0, 964.0, 679.0, 2.0], "num_keypoint": 16}, {"img_no": 1391298, "person_no": 1, "bbox": [798.0, 281.0, 1126.0, 1018.0], "keypoints": [982.0, 849.0, 2.0, 975.0, 707.0, 2.0, 983.0, 575.0, 2.0, 1019.0, 578.0, 2.0, 1037.0, 756.0, 2.0, 1052.0, 902.0, 2.0, 999.0, 576.0, 1.0, 968.0, 481.0, 2.0, 936.0, 391.0, 2.0, 897.0, 306.0, 2.0, 903.0, 633.0, 2.0, 923.0, 541.0, 2.0, 920.0, 408.0, 2.0, 1003.0, 428.0, 2.0, 1023.0, 565.0, 2.0, 964.0, 679.0, 2.0], "num_keypoint": 16}, {"img_no": 1391299, "person_no": 1, "bbox": [798.0, 281.0, 1126.0, 1018.0], "keypoints": [982.0, 849.0, 2.0, 975.0, 707.0, 2.0, 983.0, 575.0, 2.0, 1019.0, 578.0, 2.0, 1037.0, 756.0, 2.0, 1052.0, 902.0, 2.0, 999.0, 576.0, 1.0, 968.0, 481.0, 2.0, 936.0, 391.0, 2.0, 897.0, 306.0, 2.0, 838.0, 548.0, 2.0, 900.0, 475.0, 2.0, 920.0, 408.0, 2.0, 1003.0, 428.0, 2.0, 1023.0, 565.0, 2.0, 1017.0, 671.0, 2.0], "num_keypoint": 16}, {"img_no": 1391300, "person_no": 1, "bbox": [778.0, 282.0, 1125.0, 1019.0], "keypoints": [982.0, 849.0, 2.0, 975.0, 707.0, 2.0, 983.0, 575.0, 2.0, 1019.0, 578.0, 2.0, 1037.0, 756.0, 2.0, 1052.0, 902.0, 2.0, 999.0, 576.0, 2.0, 968.0, 481.0, 2.0, 936.0, 391.0, 2.0, 897.0, 306.0, 2.0, 833.0, 418.0, 2.0, 887.0, 421.0, 2.0, 920.0, 408.0, 1.0, 1003.0, 428.0, 2.0, 1087.0, 501.0, 2.0, 1085.0, 574.0, 2.0], "num_keypoint": 16}, {"img_no": 1391301, "person_no": 1, "bbox": [778.0, 282.0, 1125.0, 1019.0], "keypoints": [982.0, 849.0, 2.0, 975.0, 707.0, 2.0, 983.0, 575.0, 2.0, 1019.0, 578.0, 2.0, 1037.0, 756.0, 2.0, 1052.0, 902.0, 2.0, 999.0, 576.0, 2.0, 968.0, 481.0, 2.0, 936.0, 391.0, 2.0, 897.0, 306.0, 2.0, 833.0, 418.0, 2.0, 887.0, 414.0, 2.0, 920.0, 408.0, 1.0, 1003.0, 428.0, 2.0, 1087.0, 501.0, 2.0, 1085.0, 574.0, 2.0], "num_keypoint": 16}, {"img_no": 1391302, "person_no": 1, "bbox": [778.0, 282.0, 1125.0, 1019.0], "keypoints": [982.0, 849.0, 2.0, 975.0, 707.0, 2.0, 983.0, 575.0, 2.0, 1019.0, 578.0, 2.0, 1037.0, 756.0, 2.0, 1052.0, 902.0, 2.0, 999.0, 576.0, 2.0, 968.0, 481.0, 2.0, 936.0, 391.0, 2.0, 897.0, 297.0, 2.0, 838.0, 456.0, 2.0, 903.0, 430.0, 2.0, 920.0, 408.0, 1.0, 1003.0, 428.0, 2.0, 1076.0, 504.0, 2.0, 1084.0, 589.0, 2.0], "num_keypoint": 16}, {"img_no": 1391303, "person_no": 1, "bbox": [778.0, 282.0, 1125.0, 1019.0], "keypoints": [982.0, 849.0, 2.0, 975.0, 707.0, 2.0, 983.0, 575.0, 2.0, 1019.0, 578.0, 2.0, 1037.0, 756.0, 2.0, 1052.0, 902.0, 2.0, 999.0, 576.0, 2.0, 968.0, 481.0, 2.0, 936.0, 391.0, 2.0, 897.0, 297.0, 2.0, 872.0, 561.0, 2.0, 918.0, 478.0, 2.0, 920.0, 408.0, 2.0, 1003.0, 428.0, 2.0, 1050.0, 576.0, 2.0, 1041.0, 671.0, 2.0], "num_keypoint": 16}, {"img_no": 1391304, "person_no": 1, "bbox": [778.0, 282.0, 1125.0, 1019.0], "keypoints": [982.0, 849.0, 2.0, 956.0, 693.0, 2.0, 983.0, 575.0, 2.0, 1019.0, 578.0, 2.0, 1037.0, 756.0, 2.0, 1052.0, 902.0, 2.0, 999.0, 576.0, 2.0, 968.0, 481.0, 2.0, 936.0, 391.0, 2.0, 897.0, 297.0, 2.0, 898.0, 611.0, 2.0, 923.0, 524.0, 2.0, 911.0, 420.0, 2.0, 1003.0, 428.0, 2.0, 1037.0, 583.0, 2.0, 983.0, 690.0, 2.0], "num_keypoint": 16}]}