{"images": [{"video_no": 69485, "img_no": 1391215, "img_path": "/201909_3W_B1/20190917/28-8-Camera 11 (805316627)/28-8-Camera 11 (805316627)_9.jpg", "width": 1920, "height": 1080, "action_category": "28"}, {"video_no": 69485, "img_no": 1391216, "img_path": "/201909_3W_B1/20190917/28-8-Camera 11 (805316627)/28-8-Camera 11 (805316627)_19.jpg", "width": 1920, "height": 1080, "action_category": "28"}, {"video_no": 69485, "img_no": 1391217, "img_path": "/201909_3W_B1/20190917/28-8-Camera 11 (805316627)/28-8-Camera 11 (805316627)_29.jpg", "width": 1920, "height": 1080, "action_category": "28"}, {"video_no": 69485, "img_no": 1391218, "img_path": "/201909_3W_B1/20190917/28-8-Camera 11 (805316627)/28-8-Camera 11 (805316627)_39.jpg", "width": 1920, "height": 1080, "action_category": "28"}, {"video_no": 69485, "img_no": 1391219, "img_path": "/201909_3W_B1/20190917/28-8-Camera 11 (805316627)/28-8-Camera 11 (805316627)_49.jpg", "width": 1920, "height": 1080, "action_category": "28"}, {"video_no": 69485, "img_no": 1391220, "img_path": "/201909_3W_B1/20190917/28-8-Camera 11 (805316627)/28-8-Camera 11 (805316627)_59.jpg", "width": 1920, "height": 1080, "action_category": "28"}, {"video_no": 69485, "img_no": 1391221, "img_path": "/201909_3W_B1/20190917/28-8-Camera 11 (805316627)/28-8-Camera 11 (805316627)_69.jpg", "width": 1920, "height": 1080, "action_category": "28"}, {"video_no": 69485, "img_no": 1391222, "img_path": "/201909_3W_B1/20190917/28-8-Camera 11 (805316627)/28-8-Camera 11 (805316627)_79.jpg", "width": 1920, "height": 1080, "action_category": "28"}, {"video_no": 69485, "img_no": 1391223, "img_path": "/201909_3W_B1/20190917/28-8-Camera 11 (805316627)/28-8-Camera 11 (805316627)_89.jpg", "width": 1920, "height": 1080, "action_category": "28"}, {"video_no": 69485, "img_no": 1391224, "img_path": "/201909_3W_B1/20190917/28-8-Camera 11 (805316627)/28-8-Camera 11 (805316627)_99.jpg", "width": 1920, "height": 1080, "action_category": "28"}, {"video_no": 69485, "img_no": 1391225, "img_path": "/201909_3W_B1/20190917/28-8-Camera 11 (805316627)/28-8-Camera 11 (805316627)_109.jpg", "width": 1920, "height": 1080, "action_category": "28"}, {"video_no": 69485, "img_no": 1391226, "img_path": "/201909_3W_B1/20190917/28-8-Camera 11 (805316627)/28-8-Camera 11 (805316627)_119.jpg", "width": 1920, "height": 1080, "action_category": "28"}, {"video_no": 69485, "img_no": 1391227, "img_path": "/201909_3W_B1/20190917/28-8-Camera 11 (805316627)/28-8-Camera 11 (805316627)_129.jpg", "width": 1920, "height": 1080, "action_category": "28"}, {"video_no": 69485, "img_no": 1391228, "img_path": "/201909_3W_B1/20190917/28-8-Camera 11 (805316627)/28-8-Camera 11 (805316627)_139.jpg", "width": 1920, "height": 1080, "action_category": "28"}, {"video_no": 69485, "img_no": 1391229, "img_path": "/201909_3W_B1/20190917/28-8-Camera 11 (805316627)/28-8-Camera 11 (805316627)_149.jpg", "width": 1920, "height": 1080, "action_category": "28"}, {"video_no": 69485, "img_no": 1391230, "img_path": "/201909_3W_B1/20190917/28-8-Camera 11 (805316627)/28-8-Camera 11 (805316627)_159.jpg", "width": 1920, "height": 1080, "action_category": "28"}, {"video_no": 69485, "img_no": 1391231, "img_path": "/201909_3W_B1/20190917/28-8-Camera 11 (805316627)/28-8-Camera 11 (805316627)_169.jpg", "width": 1920, "height": 1080, "action_category": "28"}, {"video_no": 69485, "img_no": 1391232, "img_path": "/201909_3W_B1/20190917/28-8-Camera 11 (805316627)/28-8-Camera 11 (805316627)_179.jpg", "width": 1920, "height": 1080, "action_category": "28"}], "categories": [{"supercategory": "person", "id": 1, "name": "person", "keypoints": ["right_ankle_x", "right_ankle_y", "right_ankle_view", "right_knee_x", "right_knee_y", "right_knee_view", "right_hip_x", "right_hip_y", "right_hip_view", "left_hip_x", "left_hip_y", "left_hip_view", "left_knee_x", "left_knee_y", "left_knee_view", "left_ankle_x", "left_ankle_y", "left_ankle_view", "pelvis_x", "pelvis_y", "pelvis_view", "throax_x", "throax_y", "throax_view", "neck_x", "neck_y", "neck_view", "head_top_x", "head_top_y", "head_top_view", "right_wrist_x", "right_wrist_y", "right_wrist_view", "right_elbow_x", "right_elbow_y", "right_elbow_view", "right_shoulder_x", "right_shoulder_y", "right_shoulder_view", "left_shoulder_x", "left_shoulder_y", "left_shoulder_view", "left_elbow_x", "left_elbow_y", "left_elbow_view", "left_wrist_x", "left_wrist_y", "left_wrist_view"]}], "annotations": [{"img_no": 1391215, "person_no": 1, "bbox": [747.0, 120.0, 1096.0, 879.0], "keypoints": [978.0, 809.0, 2.0, 965.0, 652.0, 2.0, 943.0, 435.0, 2.0, 860.0, 439.0, 2.0, 843.0, 642.0, 2.0, 821.0, 791.0, 2.0, 895.0, 440.0, 2.0, 907.0, 321.0, 2.0, 920.0, 221.0, 2.0, 942.0, 144.0, 2.0, 1053.0, 505.0, 2.0, 1023.0, 409.0, 2.0, 991.0, 265.0, 2.0, 854.0, 250.0, 2.0, 797.0, 383.0, 2.0, 804.0, 477.0, 2.0], "num_keypoint": 16}, {"img_no": 1391216, "person_no": 1, "bbox": [747.0, 120.0, 1096.0, 879.0], "keypoints": [978.0, 809.0, 2.0, 965.0, 652.0, 2.0, 943.0, 435.0, 2.0, 860.0, 439.0, 2.0, 843.0, 642.0, 2.0, 821.0, 791.0, 2.0, 895.0, 440.0, 2.0, 900.0, 325.0, 2.0, 909.0, 225.0, 2.0, 916.0, 150.0, 2.0, 1022.0, 512.0, 2.0, 1005.0, 402.0, 2.0, 991.0, 265.0, 2.0, 854.0, 250.0, 2.0, 797.0, 383.0, 2.0, 804.0, 477.0, 2.0], "num_keypoint": 16}, {"img_no": 1391217, "person_no": 1, "bbox": [771.0, 150.0, 1069.0, 865.0], "keypoints": [978.0, 809.0, 2.0, 965.0, 652.0, 2.0, 943.0, 435.0, 2.0, 860.0, 439.0, 2.0, 843.0, 642.0, 2.0, 821.0, 791.0, 2.0, 895.0, 440.0, 2.0, 912.0, 337.0, 2.0, 922.0, 247.0, 2.0, 939.0, 170.0, 2.0, 1013.0, 532.0, 2.0, 1010.0, 442.0, 2.0, 1012.0, 311.0, 2.0, 862.0, 290.0, 2.0, 830.0, 414.0, 2.0, 854.0, 545.0, 1.0], "num_keypoint": 16}, {"img_no": 1391218, "person_no": 1, "bbox": [771.0, 150.0, 1069.0, 865.0], "keypoints": [978.0, 809.0, 2.0, 965.0, 652.0, 2.0, 943.0, 435.0, 2.0, 860.0, 439.0, 2.0, 843.0, 642.0, 2.0, 821.0, 791.0, 2.0, 895.0, 440.0, 2.0, 912.0, 337.0, 2.0, 922.0, 247.0, 2.0, 939.0, 170.0, 2.0, 1004.0, 537.0, 2.0, 1007.0, 441.0, 2.0, 1003.0, 314.0, 2.0, 862.0, 290.0, 2.0, 830.0, 414.0, 2.0, 854.0, 545.0, 1.0], "num_keypoint": 16}, {"img_no": 1391219, "person_no": 1, "bbox": [768.0, 146.0, 1121.0, 861.0], "keypoints": [978.0, 809.0, 2.0, 965.0, 652.0, 2.0, 943.0, 435.0, 2.0, 860.0, 439.0, 2.0, 843.0, 642.0, 2.0, 821.0, 791.0, 2.0, 895.0, 440.0, 2.0, 912.0, 337.0, 2.0, 922.0, 247.0, 2.0, 939.0, 170.0, 2.0, 1087.0, 510.0, 2.0, 1048.0, 430.0, 2.0, 981.0, 297.0, 2.0, 862.0, 290.0, 2.0, 785.0, 402.0, 2.0, 795.0, 506.0, 2.0], "num_keypoint": 16}, {"img_no": 1391220, "person_no": 1, "bbox": [661.0, 146.0, 1216.0, 861.0], "keypoints": [978.0, 809.0, 2.0, 965.0, 652.0, 2.0, 943.0, 435.0, 2.0, 860.0, 439.0, 2.0, 843.0, 642.0, 2.0, 821.0, 791.0, 2.0, 895.0, 440.0, 2.0, 912.0, 337.0, 2.0, 922.0, 247.0, 2.0, 939.0, 170.0, 2.0, 1180.0, 402.0, 2.0, 1087.0, 362.0, 2.0, 981.0, 297.0, 2.0, 862.0, 290.0, 2.0, 754.0, 350.0, 2.0, 694.0, 406.0, 2.0], "num_keypoint": 16}, {"img_no": 1391221, "person_no": 1, "bbox": [637.0, 144.0, 1247.0, 859.0], "keypoints": [978.0, 809.0, 2.0, 965.0, 652.0, 2.0, 933.0, 444.0, 2.0, 835.0, 439.0, 2.0, 817.0, 641.0, 2.0, 821.0, 791.0, 2.0, 882.0, 440.0, 2.0, 903.0, 335.0, 2.0, 922.0, 247.0, 2.0, 939.0, 170.0, 2.0, 1191.0, 357.0, 2.0, 1067.0, 330.0, 2.0, 981.0, 297.0, 2.0, 862.0, 290.0, 2.0, 739.0, 312.0, 2.0, 678.0, 353.0, 2.0], "num_keypoint": 16}, {"img_no": 1391222, "person_no": 1, "bbox": [637.0, 144.0, 1247.0, 859.0], "keypoints": [978.0, 809.0, 2.0, 965.0, 652.0, 2.0, 933.0, 444.0, 2.0, 835.0, 439.0, 2.0, 817.0, 641.0, 2.0, 821.0, 791.0, 2.0, 882.0, 440.0, 2.0, 903.0, 335.0, 2.0, 922.0, 247.0, 2.0, 939.0, 170.0, 2.0, 1181.0, 398.0, 2.0, 1083.0, 346.0, 2.0, 981.0, 297.0, 2.0, 862.0, 290.0, 2.0, 750.0, 321.0, 2.0, 701.0, 391.0, 2.0], "num_keypoint": 16}, {"img_no": 1391223, "person_no": 1, "bbox": [637.0, 144.0, 1247.0, 859.0], "keypoints": [978.0, 809.0, 2.0, 965.0, 652.0, 2.0, 933.0, 444.0, 2.0, 835.0, 439.0, 2.0, 817.0, 641.0, 2.0, 821.0, 791.0, 2.0, 882.0, 440.0, 2.0, 903.0, 335.0, 2.0, 922.0, 247.0, 2.0, 939.0, 170.0, 2.0, 1111.0, 496.0, 2.0, 1050.0, 399.0, 2.0, 981.0, 297.0, 2.0, 862.0, 290.0, 2.0, 776.0, 395.0, 2.0, 760.0, 479.0, 2.0], "num_keypoint": 16}, {"img_no": 1391224, "person_no": 1, "bbox": [721.0, 147.0, 1084.0, 862.0], "keypoints": [978.0, 809.0, 2.0, 965.0, 652.0, 2.0, 933.0, 444.0, 2.0, 835.0, 439.0, 2.0, 817.0, 641.0, 2.0, 821.0, 791.0, 2.0, 882.0, 440.0, 2.0, 903.0, 335.0, 2.0, 922.0, 247.0, 2.0, 939.0, 170.0, 2.0, 1034.0, 523.0, 2.0, 1016.0, 428.0, 2.0, 981.0, 297.0, 2.0, 846.0, 284.0, 2.0, 815.0, 392.0, 2.0, 820.0, 507.0, 1.0], "num_keypoint": 16}, {"img_no": 1391225, "person_no": 1, "bbox": [721.0, 147.0, 1084.0, 862.0], "keypoints": [978.0, 809.0, 2.0, 965.0, 652.0, 2.0, 933.0, 444.0, 2.0, 835.0, 439.0, 2.0, 817.0, 641.0, 2.0, 821.0, 791.0, 2.0, 882.0, 440.0, 2.0, 903.0, 335.0, 2.0, 922.0, 247.0, 2.0, 939.0, 170.0, 2.0, 971.0, 535.0, 1.0, 1002.0, 428.0, 2.0, 981.0, 297.0, 2.0, 846.0, 284.0, 2.0, 815.0, 392.0, 2.0, 859.0, 543.0, 1.0], "num_keypoint": 16}, {"img_no": 1391226, "person_no": 1, "bbox": [721.0, 147.0, 1084.0, 862.0], "keypoints": [978.0, 809.0, 2.0, 965.0, 652.0, 2.0, 933.0, 444.0, 2.0, 835.0, 439.0, 2.0, 817.0, 641.0, 2.0, 821.0, 791.0, 2.0, 882.0, 440.0, 2.0, 903.0, 335.0, 2.0, 922.0, 247.0, 2.0, 939.0, 170.0, 2.0, 1003.0, 534.0, 2.0, 1002.0, 428.0, 2.0, 981.0, 297.0, 2.0, 835.0, 292.0, 2.0, 819.0, 402.0, 2.0, 859.0, 543.0, 1.0], "num_keypoint": 16}, {"img_no": 1391227, "person_no": 1, "bbox": [721.0, 147.0, 1156.0, 862.0], "keypoints": [978.0, 809.0, 2.0, 965.0, 652.0, 2.0, 933.0, 444.0, 2.0, 835.0, 439.0, 2.0, 817.0, 641.0, 2.0, 821.0, 791.0, 2.0, 882.0, 440.0, 2.0, 903.0, 335.0, 2.0, 922.0, 247.0, 2.0, 939.0, 170.0, 2.0, 1111.0, 476.0, 2.0, 1054.0, 394.0, 2.0, 981.0, 297.0, 2.0, 835.0, 292.0, 2.0, 768.0, 386.0, 2.0, 759.0, 480.0, 2.0], "num_keypoint": 16}, {"img_no": 1391228, "person_no": 1, "bbox": [627.0, 147.0, 1242.0, 862.0], "keypoints": [978.0, 809.0, 2.0, 965.0, 652.0, 2.0, 933.0, 444.0, 2.0, 835.0, 439.0, 2.0, 817.0, 641.0, 2.0, 821.0, 791.0, 2.0, 882.0, 440.0, 2.0, 903.0, 335.0, 2.0, 922.0, 247.0, 2.0, 939.0, 170.0, 2.0, 1191.0, 355.0, 2.0, 1097.0, 333.0, 2.0, 981.0, 297.0, 2.0, 835.0, 292.0, 2.0, 732.0, 337.0, 2.0, 655.0, 382.0, 2.0], "num_keypoint": 16}, {"img_no": 1391229, "person_no": 1, "bbox": [627.0, 147.0, 1242.0, 862.0], "keypoints": [978.0, 809.0, 2.0, 965.0, 652.0, 2.0, 933.0, 444.0, 2.0, 835.0, 439.0, 2.0, 817.0, 641.0, 2.0, 821.0, 791.0, 2.0, 882.0, 440.0, 2.0, 903.0, 335.0, 2.0, 922.0, 247.0, 2.0, 939.0, 170.0, 2.0, 1191.0, 355.0, 2.0, 1097.0, 333.0, 2.0, 981.0, 297.0, 2.0, 835.0, 292.0, 2.0, 735.0, 329.0, 2.0, 655.0, 361.0, 2.0], "num_keypoint": 16}, {"img_no": 1391230, "person_no": 1, "bbox": [627.0, 147.0, 1222.0, 862.0], "keypoints": [978.0, 809.0, 2.0, 965.0, 652.0, 2.0, 933.0, 444.0, 2.0, 835.0, 439.0, 2.0, 817.0, 641.0, 2.0, 821.0, 791.0, 2.0, 882.0, 440.0, 2.0, 903.0, 335.0, 2.0, 922.0, 247.0, 2.0, 939.0, 170.0, 2.0, 1187.0, 384.0, 2.0, 1094.0, 352.0, 2.0, 981.0, 297.0, 2.0, 835.0, 292.0, 2.0, 735.0, 329.0, 2.0, 664.0, 383.0, 2.0], "num_keypoint": 16}, {"img_no": 1391231, "person_no": 1, "bbox": [691.0, 147.0, 1167.0, 862.0], "keypoints": [978.0, 809.0, 2.0, 965.0, 652.0, 2.0, 933.0, 444.0, 2.0, 835.0, 439.0, 2.0, 817.0, 641.0, 2.0, 821.0, 791.0, 2.0, 882.0, 440.0, 2.0, 903.0, 335.0, 2.0, 922.0, 247.0, 2.0, 939.0, 170.0, 2.0, 1123.0, 488.0, 2.0, 1050.0, 420.0, 2.0, 981.0, 297.0, 2.0, 835.0, 292.0, 2.0, 752.0, 378.0, 2.0, 731.0, 475.0, 2.0], "num_keypoint": 16}, {"img_no": 1391232, "person_no": 1, "bbox": [739.0, 147.0, 1066.0, 862.0], "keypoints": [978.0, 809.0, 2.0, 965.0, 652.0, 2.0, 933.0, 444.0, 2.0, 835.0, 439.0, 2.0, 817.0, 641.0, 2.0, 821.0, 791.0, 2.0, 882.0, 440.0, 2.0, 903.0, 335.0, 2.0, 922.0, 247.0, 2.0, 939.0, 170.0, 2.0, 1016.0, 526.0, 2.0, 1005.0, 425.0, 2.0, 981.0, 297.0, 2.0, 835.0, 292.0, 2.0, 779.0, 405.0, 2.0, 846.0, 481.0, 1.0], "num_keypoint": 16}]}